django_ghoster-0.1.2.dist-info/DESCRIPTION.rst
django_ghoster-0.1.2.dist-info/METADATA
django_ghoster-0.1.2.dist-info/RECORD
django_ghoster-0.1.2.dist-info/WHEEL
django_ghoster-0.1.2.dist-info/metadata.json
django_ghoster-0.1.2.dist-info/top_level.txt
ghoster/__init__.py
ghoster/admin.py
ghoster/apps.py
ghoster/forms.py
ghoster/models.py
ghoster/note.py
ghoster/tests.py
ghoster/views.py
ghoster/widgets.py
ghoster/locale/zh_Hant/LC_MESSAGES/django.mo
ghoster/locale/zh_Hant/LC_MESSAGES/django.po
ghoster/locale/zh_Hant/LC_MESSAGES/djangojs.mo
ghoster/locale/zh_Hant/LC_MESSAGES/djangojs.po
ghoster/migrations/__init__.py
ghoster/static/admin/assets/css/.DS_Store
ghoster/static/admin/assets/css/app.css
ghoster/static/admin/assets/css/docs.min.css
ghoster/static/admin/assets/css/style.css
ghoster/static/admin/assets/css/style.css.map
ghoster/static/admin/assets/css/style.min.css
ghoster/static/admin/assets/fonts/FontAwesome.otf
ghoster/static/admin/assets/fonts/Simple-Line-Icons.eot
ghoster/static/admin/assets/fonts/Simple-Line-Icons.svg
ghoster/static/admin/assets/fonts/Simple-Line-Icons.ttf
ghoster/static/admin/assets/fonts/Simple-Line-Icons.woff
ghoster/static/admin/assets/fonts/Simple-Line-Icons.woff2
ghoster/static/admin/assets/fonts/fontawesome-webfont.eot
ghoster/static/admin/assets/fonts/fontawesome-webfont.svg
ghoster/static/admin/assets/fonts/fontawesome-webfont.ttf
ghoster/static/admin/assets/fonts/fontawesome-webfont.woff
ghoster/static/admin/assets/fonts/fontawesome-webfont.woff2
ghoster/static/admin/assets/img/.DS_Store
ghoster/static/admin/assets/img/Sorting icons.psd
ghoster/static/admin/assets/img/favicon.ico
ghoster/static/admin/assets/img/logo-dark.png
ghoster/static/admin/assets/img/logo-light.png
ghoster/static/admin/assets/img/logo.psd
ghoster/static/admin/assets/img/select.png
ghoster/static/admin/assets/img/select2.png
ghoster/static/admin/assets/img/select2x2.png
ghoster/static/admin/assets/img/sort_asc.png
ghoster/static/admin/assets/img/sort_asc_disabled.png
ghoster/static/admin/assets/img/sort_both.png
ghoster/static/admin/assets/img/sort_desc.png
ghoster/static/admin/assets/img/sort_desc_disabled.png
