Metadata-Version: 2.0
Name: django-ghoster
Version: 0.1.2
Summary: ghoster is a admin theme which includes markdown features for Django users
Home-page: https://github.com/ZuirensGit/django-ghoster
Author: Ryan Chao
Author-email: ryanchao2012@gmail.com
License: MIT
Keywords: django markdown cms
Platform: UNKNOWN
Classifier: Development Status :: 4 - Beta
Classifier: Intended Audience :: Developers
Classifier: License :: OSI Approved :: MIT License
Classifier: Programming Language :: Python
Classifier: Framework :: Django
Classifier: Topic :: Software Development
Classifier: Topic :: Software Development :: User Interfaces
